infoupgraders/__init__.py
infoupgraders-0.0.5.dist-info/LICENSE.txt
infoupgraders-0.0.5.dist-info/METADATA
infoupgraders-0.0.5.dist-info/WHEEL
infoupgraders-0.0.5.dist-info/top_level.txt
infoupgraders-0.0.5.dist-info/RECORD
